{
	"id": "c6784e93-c1e5-4b94-b928-fa5a218c6581",
	"prevId": "0fb6c783-a629-46ee-ba13-fdbb83c99cb5",
	"version": "7",
	"dialect": "postgresql",
	"tables": {
		"public.account": {
			"name": "account",
			"schema": "",
			"columns": {
				"id": {
					"name": "id",
					"type": "text",
					"primaryKey": true,
					"notNull": true
				},
				"account_id": {
					"name": "account_id",
					"type": "text",
					"primaryKey": false,
					"notNull": true
				},
				"provider_id": {
					"name": "provider_id",
					"type": "text",
					"primaryKey": false,
					"notNull": true
				},
				"user_id": {
					"name": "user_id",
					"type": "text",
					"primaryKey": false,
					"notNull": true
				},
				"access_token": {
					"name": "access_token",
					"type": "text",
					"primaryKey": false,
					"notNull": false
				},
				"refresh_token": {
					"name": "refresh_token",
					"type": "text",
					"primaryKey": false,
					"notNull": false
				},
				"id_token": {
					"name": "id_token",
					"type": "text",
					"primaryKey": false,
					"notNull": false
				},
				"access_token_expires_at": {
					"name": "access_token_expires_at",
					"type": "timestamp",
					"primaryKey": false,
					"notNull": false
				},
				"refresh_token_expires_at": {
					"name": "refresh_token_expires_at",
					"type": "timestamp",
					"primaryKey": false,
					"notNull": false
				},
				"scope": {
					"name": "scope",
					"type": "text",
					"primaryKey": false,
					"notNull": false
				},
				"password": {
					"name": "password",
					"type": "text",
					"primaryKey": false,
					"notNull": false
				},
				"created_at": {
					"name": "created_at",
					"type": "timestamp",
					"primaryKey": false,
					"notNull": true,
					"default": "now()"
				},
				"updated_at": {
					"name": "updated_at",
					"type": "timestamp",
					"primaryKey": false,
					"notNull": true
				}
			},
			"indexes": {
				"account_userId_idx": {
					"name": "account_userId_idx",
					"columns": [
						{
							"expression": "user_id",
							"isExpression": false,
							"asc": true,
							"nulls": "last"
						}
					],
					"isUnique": false,
					"concurrently": false,
					"method": "btree",
					"with": {}
				}
			},
			"foreignKeys": {
				"account_user_id_user_id_fk": {
					"name": "account_user_id_user_id_fk",
					"tableFrom": "account",
					"tableTo": "user",
					"columnsFrom": ["user_id"],
					"columnsTo": ["id"],
					"onDelete": "cascade",
					"onUpdate": "no action"
				}
			},
			"compositePrimaryKeys": {},
			"uniqueConstraints": {},
			"policies": {},
			"checkConstraints": {},
			"isRLSEnabled": false
		},
		"public.companies": {
			"name": "companies",
			"schema": "",
			"columns": {
				"id": {
					"name": "id",
					"type": "integer",
					"primaryKey": true,
					"notNull": true
				},
				"railway_category_id": {
					"name": "railway_category_id",
					"type": "smallint",
					"primaryKey": false,
					"notNull": false
				},
				"name": {
					"name": "name",
					"type": "varchar(256)",
					"primaryKey": false,
					"notNull": true
				},
				"name_kana": {
					"name": "name_kana",
					"type": "varchar(256)",
					"primaryKey": false,
					"notNull": false
				},
				"name_formal": {
					"name": "name_formal",
					"type": "varchar(256)",
					"primaryKey": false,
					"notNull": false
				},
				"name_romaji": {
					"name": "name_romaji",
					"type": "varchar(256)",
					"primaryKey": false,
					"notNull": false
				},
				"name_en": {
					"name": "name_en",
					"type": "varchar(256)",
					"primaryKey": false,
					"notNull": false
				},
				"name_en_formal": {
					"name": "name_en_formal",
					"type": "varchar(256)",
					"primaryKey": false,
					"notNull": false
				},
				"website_url": {
					"name": "website_url",
					"type": "varchar(512)",
					"primaryKey": false,
					"notNull": false
				},
				"type": {
					"name": "type",
					"type": "company_type",
					"typeSchema": "public",
					"primaryKey": false,
					"notNull": true,
					"default": "'other'"
				},
				"status": {
					"name": "status",
					"type": "entity_status",
					"typeSchema": "public",
					"primaryKey": false,
					"notNull": true,
					"default": "'active'"
				},
				"sort_order": {
					"name": "sort_order",
					"type": "integer",
					"primaryKey": false,
					"notNull": false
				}
			},
			"indexes": {},
			"foreignKeys": {},
			"compositePrimaryKeys": {},
			"uniqueConstraints": {},
			"policies": {},
			"checkConstraints": {},
			"isRLSEnabled": false
		},
		"public.lines": {
			"name": "lines",
			"schema": "",
			"columns": {
				"id": {
					"name": "id",
					"type": "integer",
					"primaryKey": true,
					"notNull": true
				},
				"company_id": {
					"name": "company_id",
					"type": "integer",
					"primaryKey": false,
					"notNull": true
				},
				"name": {
					"name": "name",
					"type": "varchar(256)",
					"primaryKey": false,
					"notNull": true
				},
				"name_kana": {
					"name": "name_kana",
					"type": "varchar(256)",
					"primaryKey": false,
					"notNull": false
				},
				"name_formal": {
					"name": "name_formal",
					"type": "varchar(256)",
					"primaryKey": false,
					"notNull": false
				},
				"name_en": {
					"name": "name_en",
					"type": "varchar(256)",
					"primaryKey": false,
					"notNull": false
				},
				"name_en_formal": {
					"name": "name_en_formal",
					"type": "varchar(256)",
					"primaryKey": false,
					"notNull": false
				},
				"color_hex": {
					"name": "color_hex",
					"type": "varchar(8)",
					"primaryKey": false,
					"notNull": false
				},
				"color_name": {
					"name": "color_name",
					"type": "varchar(64)",
					"primaryKey": false,
					"notNull": false
				},
				"type": {
					"name": "type",
					"type": "smallint",
					"primaryKey": false,
					"notNull": false
				},
				"location": {
					"name": "location",
					"type": "geometry(point)",
					"primaryKey": false,
					"notNull": false
				},
				"map_zoom": {
					"name": "map_zoom",
					"type": "smallint",
					"primaryKey": false,
					"notNull": false
				},
				"status": {
					"name": "status",
					"type": "entity_status",
					"typeSchema": "public",
					"primaryKey": false,
					"notNull": true,
					"default": "'active'"
				},
				"sort_order": {
					"name": "sort_order",
					"type": "integer",
					"primaryKey": false,
					"notNull": false
				}
			},
			"indexes": {
				"lines_location_idx": {
					"name": "lines_location_idx",
					"columns": [
						{
							"expression": "location",
							"isExpression": false,
							"asc": true,
							"nulls": "last"
						}
					],
					"isUnique": false,
					"concurrently": false,
					"method": "gist",
					"with": {}
				}
			},
			"foreignKeys": {
				"lines_company_id_companies_id_fk": {
					"name": "lines_company_id_companies_id_fk",
					"tableFrom": "lines",
					"tableTo": "companies",
					"columnsFrom": ["company_id"],
					"columnsTo": ["id"],
					"onDelete": "no action",
					"onUpdate": "no action"
				}
			},
			"compositePrimaryKeys": {},
			"uniqueConstraints": {},
			"policies": {},
			"checkConstraints": {},
			"isRLSEnabled": false
		},
		"public.prefectures": {
			"name": "prefectures",
			"schema": "",
			"columns": {
				"id": {
					"name": "id",
					"type": "smallint",
					"primaryKey": true,
					"notNull": true
				},
				"name": {
					"name": "name",
					"type": "varchar(16)",
					"primaryKey": false,
					"notNull": true
				},
				"name_kana": {
					"name": "name_kana",
					"type": "varchar(32)",
					"primaryKey": false,
					"notNull": false
				},
				"name_en": {
					"name": "name_en",
					"type": "varchar(32)",
					"primaryKey": false,
					"notNull": true
				},
				"region_id": {
					"name": "region_id",
					"type": "varchar(16)",
					"primaryKey": false,
					"notNull": true
				}
			},
			"indexes": {},
			"foreignKeys": {
				"prefectures_region_id_regions_id_fk": {
					"name": "prefectures_region_id_regions_id_fk",
					"tableFrom": "prefectures",
					"tableTo": "regions",
					"columnsFrom": ["region_id"],
					"columnsTo": ["id"],
					"onDelete": "no action",
					"onUpdate": "no action"
				}
			},
			"compositePrimaryKeys": {},
			"uniqueConstraints": {},
			"policies": {},
			"checkConstraints": {},
			"isRLSEnabled": false
		},
		"public.regions": {
			"name": "regions",
			"schema": "",
			"columns": {
				"id": {
					"name": "id",
					"type": "varchar(16)",
					"primaryKey": true,
					"notNull": true
				},
				"name": {
					"name": "name",
					"type": "varchar(32)",
					"primaryKey": false,
					"notNull": true
				},
				"name_en": {
					"name": "name_en",
					"type": "varchar(32)",
					"primaryKey": false,
					"notNull": true
				}
			},
			"indexes": {},
			"foreignKeys": {},
			"compositePrimaryKeys": {},
			"uniqueConstraints": {},
			"policies": {},
			"checkConstraints": {},
			"isRLSEnabled": false
		},
		"public.session": {
			"name": "session",
			"schema": "",
			"columns": {
				"id": {
					"name": "id",
					"type": "text",
					"primaryKey": true,
					"notNull": true
				},
				"expires_at": {
					"name": "expires_at",
					"type": "timestamp",
					"primaryKey": false,
					"notNull": true
				},
				"token": {
					"name": "token",
					"type": "text",
					"primaryKey": false,
					"notNull": true
				},
				"created_at": {
					"name": "created_at",
					"type": "timestamp",
					"primaryKey": false,
					"notNull": true,
					"default": "now()"
				},
				"updated_at": {
					"name": "updated_at",
					"type": "timestamp",
					"primaryKey": false,
					"notNull": true
				},
				"ip_address": {
					"name": "ip_address",
					"type": "text",
					"primaryKey": false,
					"notNull": false
				},
				"user_agent": {
					"name": "user_agent",
					"type": "text",
					"primaryKey": false,
					"notNull": false
				},
				"user_id": {
					"name": "user_id",
					"type": "text",
					"primaryKey": false,
					"notNull": true
				}
			},
			"indexes": {
				"session_userId_idx": {
					"name": "session_userId_idx",
					"columns": [
						{
							"expression": "user_id",
							"isExpression": false,
							"asc": true,
							"nulls": "last"
						}
					],
					"isUnique": false,
					"concurrently": false,
					"method": "btree",
					"with": {}
				}
			},
			"foreignKeys": {
				"session_user_id_user_id_fk": {
					"name": "session_user_id_user_id_fk",
					"tableFrom": "session",
					"tableTo": "user",
					"columnsFrom": ["user_id"],
					"columnsTo": ["id"],
					"onDelete": "cascade",
					"onUpdate": "no action"
				}
			},
			"compositePrimaryKeys": {},
			"uniqueConstraints": {
				"session_token_unique": {
					"name": "session_token_unique",
					"nullsNotDistinct": false,
					"columns": ["token"]
				}
			},
			"policies": {},
			"checkConstraints": {},
			"isRLSEnabled": false
		},
		"public.stations": {
			"name": "stations",
			"schema": "",
			"columns": {
				"id": {
					"name": "id",
					"type": "integer",
					"primaryKey": true,
					"notNull": true
				},
				"group_id": {
					"name": "group_id",
					"type": "integer",
					"primaryKey": false,
					"notNull": true
				},
				"name": {
					"name": "name",
					"type": "varchar(256)",
					"primaryKey": false,
					"notNull": true
				},
				"name_kana": {
					"name": "name_kana",
					"type": "varchar(256)",
					"primaryKey": false,
					"notNull": false
				},
				"name_romaji": {
					"name": "name_romaji",
					"type": "varchar(256)",
					"primaryKey": false,
					"notNull": false
				},
				"name_en": {
					"name": "name_en",
					"type": "varchar(256)",
					"primaryKey": false,
					"notNull": false
				},
				"name_en_formal": {
					"name": "name_en_formal",
					"type": "varchar(256)",
					"primaryKey": false,
					"notNull": false
				},
				"line_id": {
					"name": "line_id",
					"type": "integer",
					"primaryKey": false,
					"notNull": true
				},
				"prefecture_id": {
					"name": "prefecture_id",
					"type": "smallint",
					"primaryKey": false,
					"notNull": true
				},
				"postal_code": {
					"name": "postal_code",
					"type": "varchar(16)",
					"primaryKey": false,
					"notNull": false
				},
				"address": {
					"name": "address",
					"type": "text",
					"primaryKey": false,
					"notNull": false
				},
				"location": {
					"name": "location",
					"type": "geometry(point)",
					"primaryKey": false,
					"notNull": false
				},
				"opened_on": {
					"name": "opened_on",
					"type": "date",
					"primaryKey": false,
					"notNull": false
				},
				"closed_on": {
					"name": "closed_on",
					"type": "date",
					"primaryKey": false,
					"notNull": false
				},
				"status": {
					"name": "status",
					"type": "entity_status",
					"typeSchema": "public",
					"primaryKey": false,
					"notNull": true,
					"default": "'active'"
				},
				"sort_order": {
					"name": "sort_order",
					"type": "integer",
					"primaryKey": false,
					"notNull": false
				}
			},
			"indexes": {
				"stations_location_idx": {
					"name": "stations_location_idx",
					"columns": [
						{
							"expression": "location",
							"isExpression": false,
							"asc": true,
							"nulls": "last"
						}
					],
					"isUnique": false,
					"concurrently": false,
					"method": "gist",
					"with": {}
				}
			},
			"foreignKeys": {
				"stations_line_id_lines_id_fk": {
					"name": "stations_line_id_lines_id_fk",
					"tableFrom": "stations",
					"tableTo": "lines",
					"columnsFrom": ["line_id"],
					"columnsTo": ["id"],
					"onDelete": "no action",
					"onUpdate": "no action"
				},
				"stations_prefecture_id_prefectures_id_fk": {
					"name": "stations_prefecture_id_prefectures_id_fk",
					"tableFrom": "stations",
					"tableTo": "prefectures",
					"columnsFrom": ["prefecture_id"],
					"columnsTo": ["id"],
					"onDelete": "no action",
					"onUpdate": "no action"
				}
			},
			"compositePrimaryKeys": {},
			"uniqueConstraints": {},
			"policies": {},
			"checkConstraints": {},
			"isRLSEnabled": false
		},
		"public.user": {
			"name": "user",
			"schema": "",
			"columns": {
				"id": {
					"name": "id",
					"type": "text",
					"primaryKey": true,
					"notNull": true
				},
				"name": {
					"name": "name",
					"type": "text",
					"primaryKey": false,
					"notNull": true
				},
				"email": {
					"name": "email",
					"type": "text",
					"primaryKey": false,
					"notNull": true
				},
				"email_verified": {
					"name": "email_verified",
					"type": "boolean",
					"primaryKey": false,
					"notNull": true,
					"default": false
				},
				"image": {
					"name": "image",
					"type": "text",
					"primaryKey": false,
					"notNull": false
				},
				"created_at": {
					"name": "created_at",
					"type": "timestamp",
					"primaryKey": false,
					"notNull": true,
					"default": "now()"
				},
				"updated_at": {
					"name": "updated_at",
					"type": "timestamp",
					"primaryKey": false,
					"notNull": true,
					"default": "now()"
				}
			},
			"indexes": {},
			"foreignKeys": {},
			"compositePrimaryKeys": {},
			"uniqueConstraints": {
				"user_email_unique": {
					"name": "user_email_unique",
					"nullsNotDistinct": false,
					"columns": ["email"]
				}
			},
			"policies": {},
			"checkConstraints": {},
			"isRLSEnabled": false
		},
		"public.verification": {
			"name": "verification",
			"schema": "",
			"columns": {
				"id": {
					"name": "id",
					"type": "text",
					"primaryKey": true,
					"notNull": true
				},
				"identifier": {
					"name": "identifier",
					"type": "text",
					"primaryKey": false,
					"notNull": true
				},
				"value": {
					"name": "value",
					"type": "text",
					"primaryKey": false,
					"notNull": true
				},
				"expires_at": {
					"name": "expires_at",
					"type": "timestamp",
					"primaryKey": false,
					"notNull": true
				},
				"created_at": {
					"name": "created_at",
					"type": "timestamp",
					"primaryKey": false,
					"notNull": true,
					"default": "now()"
				},
				"updated_at": {
					"name": "updated_at",
					"type": "timestamp",
					"primaryKey": false,
					"notNull": true,
					"default": "now()"
				}
			},
			"indexes": {
				"verification_identifier_idx": {
					"name": "verification_identifier_idx",
					"columns": [
						{
							"expression": "identifier",
							"isExpression": false,
							"asc": true,
							"nulls": "last"
						}
					],
					"isUnique": false,
					"concurrently": false,
					"method": "btree",
					"with": {}
				}
			},
			"foreignKeys": {},
			"compositePrimaryKeys": {},
			"uniqueConstraints": {},
			"policies": {},
			"checkConstraints": {},
			"isRLSEnabled": false
		}
	},
	"enums": {
		"public.company_type": {
			"name": "company_type",
			"schema": "public",
			"values": ["other", "jr", "major_private", "semi_major"]
		},
		"public.entity_status": {
			"name": "entity_status",
			"schema": "public",
			"values": ["active", "pre_opening", "defunct"]
		}
	},
	"schemas": {},
	"sequences": {},
	"roles": {},
	"policies": {},
	"views": {},
	"_meta": {
		"columns": {},
		"schemas": {},
		"tables": {}
	}
}
